{"chunk_definitions":[{"row":14,"row_count":1,"visible":true,"expansion_state":0,"options":{"engine":"R","label":"unnamed-chunk-2"},"document_id":"40BC628E","chunk_id":"cjyz3c8i2sg1j","chunk_label":"unnamed-chunk-1"},{"row":25,"row_count":1,"visible":true,"expansion_state":0,"options":{"engine":"r","label":"unnamed-chunk-3"},"document_id":"40BC628E","chunk_id":"c3j16v8cirfwr","chunk_label":"unnamed-chunk-2"},{"row":31,"row_count":1,"visible":true,"expansion_state":0,"options":{"engine":"r","label":"unnamed-chunk-4"},"document_id":"40BC628E","chunk_id":"cd2din5ibqm7o","chunk_label":"unnamed-chunk-3"},{"row":40,"row_count":1,"visible":true,"expansion_state":0,"options":{"engine":"R","label":"unnamed-chunk-5"},"document_id":"40BC628E","chunk_id":"ctq4jzxiym3wb","chunk_label":"unnamed-chunk-4"},{"row":50,"row_count":1,"visible":true,"expansion_state":0,"options":{"engine":"r","label":"unnamed-chunk-6"},"document_id":"40BC628E","chunk_id":"c9r28zuqhluhi","chunk_label":"unnamed-chunk-5"},{"row":54,"row_count":1,"visible":true,"expansion_state":0,"options":{"engine":"r","label":"unnamed-chunk-7"},"document_id":"40BC628E","chunk_id":"cn92cxq0bysbj","chunk_label":"unnamed-chunk-6"},{"row":63,"row_count":1,"visible":true,"expansion_state":0,"options":{"engine":"r","label":"unnamed-chunk-8"},"document_id":"40BC628E","chunk_id":"cq41enbo7veim","chunk_label":"unnamed-chunk-7"},{"row":69,"row_count":1,"visible":true,"expansion_state":0,"options":{"engine":"r","label":"unnamed-chunk-1"},"document_id":"40BC628E","chunk_id":"cl8s2wusbsd22","chunk_label":"unnamed-chunk-8"}],"doc_write_time":1618285740}